{
  "id": "13",
  "palette": [
    "#020202",
    "#122122",
    "#234c4c",
    "#1a737e",
    "#676761",
    "#26a9a8",
    "#04a6f0",
    "#918e8c",
    "#e28f4f",
    "#0ed2ec",
    "#23f1ca",
    "#09f6fd",
    "#f8b36a",
    "#60f9da",
    "#fdd38c",
    "#cacccf",
    "#fefdfc"
  ],
  "numbers": [
    {
      "number": 1,
      "x": 522,
      "y": 413,
      "color_index": 0
    },
    {
      "number": 7,
      "x": 438,
      "y": 398,
      "color_index": 6
    },
    {
      "number": 7,
      "x": 411,
      "y": 847,
      "color_index": 6
    },
    {
      "number": 9,
      "x": 274,
      "y": 275,
      "color_index": 8
    },
    {
      "number": 9,
      "x": 750,
      "y": 276,
      "color_index": 8
    },
    {
      "number": 10,
      "x": 479,
      "y": 484,
      "color_index": 9
    },
    {
      "number": 10,
      "x": 546,
      "y": 483,
      "color_index": 9
    },
    {
      "number": 10,
      "x": 245,
      "y": 513,
      "color_index": 9
    },
    {
      "number": 10,
      "x": 834,
      "y": 675,
      "color_index": 9
    },
    {
      "number": 10,
      "x": 734,
      "y": 731,
      "color_index": 9
    },
    {
      "number": 10,
      "x": 656,
      "y": 888,
      "color_index": 9
    },
    {
      "number": 11,
      "x": 514,
      "y": 690,
      "color_index": 10
    },
    {
      "number": 12,
      "x": 507,
      "y": 477,
      "color_index": 11
    },
    {
      "number": 13,
      "x": 751,
      "y": 232,
      "color_index": 12
    },
    {
      "number": 13,
      "x": 273,
      "y": 228,
      "color_index": 12
    },
    {
      "number": 14,
      "x": 413,
      "y": 190,
      "color_index": 13
    },
    {
      "number": 14,
      "x": 716,
      "y": 284,
      "color_index": 13
    },
    {
      "number": 14,
      "x": 319,
      "y": 278,
      "color_index": 13
    },
    {
      "number": 14,
      "x": 307,
      "y": 317,
      "color_index": 13
    },
    {
      "number": 14,
      "x": 752,
      "y": 351,
      "color_index": 13
    },
    {
      "number": 14,
      "x": 242,
      "y": 424,
      "color_index": 13
    },
    {
      "number": 15,
      "x": 289,
      "y": 174,
      "color_index": 14
    },
    {
      "number": 15,
      "x": 734,
      "y": 173,
      "color_index": 14
    },
    {
      "number": 17,
      "x": 614,
      "y": 427,
      "color_index": 16
    }
  ],
  "dimensions": {
    "w": 1024,
    "h": 1024
  },
  "has_reward": true,
  "background_id": 255,
  "line_id": 254
}